[
  {
    "id": 1,
    "titre": "Assistant administratif",
    "entreprise": "Etat de Vaud",
    "lieu": "Lausanne",
    "taux": "100%",
    "contrat": "CDI",
    "salaire": "6500",
    "secteur": "Administration",
    "teletravail": true,
    "experience": "2 ans",
    "langues": ["Français","Anglais"],
    "niveau": "Intermédiaire",
    "competences": ["Excel","Office 365","Organisation"],
    "scoreIA": 84,
    "datePublication": "2026-06-01",
    "source": "Jobup",
    "url": ""
  },
  {
    "id": 2,
    "titre": "Employé de commerce",
    "entreprise": "Ville de Lausanne",
    "lieu": "Lausanne",
    "taux": "100%",
    "contrat": "CDI",
    "salaire": "6200",
    "secteur": "Administration",
    "teletravail": true,
    "experience": "1 an",
    "langues": ["Français"],
    "niveau": "Junior",
    "competences": ["Excel","Accueil","Classement"],
    "scoreIA": 82,
    "datePublication": "2026-06-02",
    "source": "Jobup",
    "url": ""
  },
  {
    "id": 3,
    "titre": "Gestionnaire de dossiers",
    "entreprise": "Canton de Vaud",
    "lieu": "Lausanne",
    "taux": "100%",
    "contrat": "CDI",
    "salaire": "6800",
    "secteur": "Administration",
    "teletravail": true,
    "experience": "2 ans",
    "langues": ["Français"],
    "niveau": "Intermédiaire",
    "competences": ["SAP","Gestion","Organisation"],
    "scoreIA": 88,
    "datePublication": "2026-06-02",
    "source": "Jobup",
    "url": ""
  },
  {
    "id": 4,
    "titre": "Technicien informatique",
    "entreprise": "EPFL",
    "lieu": "Ecublens",
    "taux": "100%",
    "contrat": "CDI",
    "salaire": "7200",
    "secteur": "Informatique",
    "teletravail": true,
    "experience": "2 ans",
    "langues": ["Français","Anglais"],
    "niveau": "Intermédiaire",
    "competences": ["Support","Windows","Réseau"],
    "scoreIA": 91,
    "datePublication": "2026-06-03",
    "source": "Jobup",
    "url": ""
  },
  {
    "id": 5,
    "titre": "Support IT",
    "entreprise": "CHUV",
    "lieu": "Lausanne",
    "taux": "100%",
    "contrat": "CDI",
    "salaire": "7000",
    "secteur": "Informatique",
    "teletravail": false,
    "experience": "2 ans",
    "langues": ["Français"],
    "niveau": "Intermédiaire",
    "competences": ["Support","Office 365","Active Directory"],
    "scoreIA": 87,
    "datePublication": "2026-06-03",
    "source": "Jobup",
    "url": ""
  },
  {
    "id": 6,
    "titre": "Assistant RH",
    "entreprise": "Migros Vaud",
    "lieu": "Ecublens",
    "taux": "80%",
    "contrat": "CDI",
    "salaire": "5900",
    "secteur": "RH",
    "teletravail": true,
    "experience": "1 an",
    "langues": ["Français"],
    "niveau": "Junior",
    "competences": ["RH","Administration","Excel"],
    "scoreIA": 80,
    "datePublication": "2026-06-04",
    "source": "Jobup",
    "url": ""
  },
  {
    "id": 7,
    "titre": "Comptable",
    "entreprise": "Romande Energie",
    "lieu": "Morges",
    "taux": "100%",
    "contrat": "CDI",
    "salaire": "7500",
    "secteur": "Finance",
    "teletravail": true,
    "experience": "3 ans",
    "langues": ["Français"],
    "niveau": "Confirmé",
    "competences": ["Comptabilité","Excel","SAP"],
    "scoreIA": 89,
    "datePublication": "2026-06-04",
    "source": "Jobup",
    "url": ""
  },
  {
    "id": 8,
    "titre": "Coordinateur administratif",
    "entreprise": "TL",
    "lieu": "Lausanne",
    "taux": "100%",
    "contrat": "CDI",
    "salaire": "6700",
    "secteur": "Administration",
    "teletravail": true,
    "experience": "2 ans",
    "langues": ["Français","Anglais"],
    "niveau": "Intermédiaire",
    "competences": ["Organisation","Excel","Reporting"],
    "scoreIA": 86,
    "datePublication": "2026-06-04",
    "source": "Jobup",
    "url": ""
  },
  {
    "id": 9,
    "titre": "Helpdesk IT",
    "entreprise": "BCV",
    "lieu": "Lausanne",
    "taux": "100%",
    "contrat": "CDI",
    "salaire": "7100",
    "secteur": "Informatique",
    "teletravail": true,
    "experience": "2 ans",
    "langues": ["Français","Anglais"],
    "niveau": "Intermédiaire",
    "competences": ["Support","Windows","Office365"],
    "scoreIA": 90,
    "datePublication": "2026-06-05",
    "source": "Jobup",
    "url": ""
  },
  {
    "id": 10,
    "titre": "Assistant de direction",
    "entreprise": "Nestlé Suisse",
    "lieu": "Vevey",
    "taux": "100%",
    "contrat": "CDI",
    "salaire": "7800",
    "secteur": "Administration",
    "teletravail": true,
    "experience": "3 ans",
    "langues": ["Français","Anglais"],
    "niveau": "Confirmé",
    "competences": ["Organisation","Office365","Reporting"],
    "scoreIA": 92,
    "datePublication": "2026-06-05",
    "source": "Jobup",
    "url": ""
  }
