[
{
"id":1,
"reference":"VD-001",
"titre":"Gestionnaire de dossiers",
"entreprise":"Canton de Vaud",
"lieu":"Lausanne",
"taux":"60%",
"secteur":"Administration publique",
"date":"2026-06-06",
"salaire":"CHF 5500 - 6500",
"description":"Gestion administrative complète de dossiers.",
"competences":"Office 365, organisation, rédaction",
"source":"Indeed",
"url":"https://ch-fr.indeed.com/q-etat-de-vaud-l-lausanne%2C-vd-emplois.html"
},
{
"id":2,
"reference":"VD-002",
"titre":"Employé de commerce",
"entreprise":"ARX Group",
"lieu":"Morges",
"taux":"70%",
"secteur":"Administration",
"date":"2026-06-06",
"salaire":"Selon profil",
"description":"Support administratif et coordination interne.",
"competences":"Excel, Word, organisation",
"source":"Indeed",
"url":"https://ch-fr.indeed.com/q-administratif-l-lausanne%2C-vd-emplois.html"
},
{
"id":3,
"reference":"VD-003",
"titre":"Assistant administratif",
"entreprise":"Entreprise Vaudoise",
"lieu":"Nyon",
"taux":"50%",
"secteur":"Administration",
"date":"2026-06-06",
"salaire":"CHF 4000 - 6500",
"description":"Gestion administrative et support opérationnel.",
"competences":"Bureautique, organisation",
"source":"Jobs.ch",
"url":"https://www.jobs.ch/fr/offres-emplois/?location=vaud&term=administrative+assistant"
},
{
"id":4,
"reference":"VD-004",
"titre":"Technicien informatique",
"entreprise":"Entreprise IT Vaud",
"lieu":"Yverdon-les-Bains",
"taux":"70%",
"secteur":"Informatique",
"date":"2026-06-06",
"salaire":"Selon expérience",
"description":"Support utilisateurs et maintenance informatique.",
"competences":"Windows, Réseau, Support",
"source":"Jobup",
"url":"https://www.jobup.ch/fr/emplois/?region=52&term=technicien+informatique+support"
},
{
"id":5,
"reference":"VD-005",
"titre":"AI Dev",
"entreprise":"Association CARA",
"lieu":"Lausanne",
"taux":"60%",
"secteur":"Intelligence Artificielle",
"date":"2026-06-06",
"salaire":"CHF 77068 - 111749",
"description":"Développement et coordination de projets numériques.",
"competences":"Python, IA, gestion de projet",
"source":"Jobs.ch",
"url":"https://www.jobs.ch/fr/offres-emplois/?location=vaud&term=artificial+intelligence"
}
]
